subnuker.py
subnuker-0.4.5.dist-info/DESCRIPTION.rst
subnuker-0.4.5.dist-info/METADATA
subnuker-0.4.5.dist-info/RECORD
subnuker-0.4.5.dist-info/WHEEL
subnuker-0.4.5.dist-info/entry_points.txt
subnuker-0.4.5.dist-info/metadata.json
subnuker-0.4.5.dist-info/pbr.json
subnuker-0.4.5.dist-info/top_level.txt
