Metadata-Version: 2.0
Name: subnuker
Version: 0.4.5
Summary: Remove spam and advertising from subtitle files
Home-page: https://github.com/brbsix/subnuker
Author: Brian Beffa
Author-email: brbsix@gmail.com
License: GPLv3
Keywords: advertising,srt,subtitle
Platform: UNKNOWN
Classifier: Development Status :: 4 - Beta
Classifier: Environment :: Console
Classifier: Intended Audience :: Developers
Classifier: Intended Audience :: End Users/Desktop
Classifier: License :: OSI Approved :: GNU General Public License v3 (GPLv3)
Classifier: Natural Language :: English
Classifier: Operating System :: POSIX
Classifier: Operating System :: POSIX :: Linux
Classifier: Programming Language :: Python :: 3
Classifier: Programming Language :: Python :: 3.0
Classifier: Programming Language :: Python :: 3.1
Classifier: Programming Language :: Python :: 3.2
Classifier: Programming Language :: Python :: 3.3
Classifier: Programming Language :: Python :: 3.4
Classifier: Programming Language :: Python :: 3 :: Only
Classifier: Topic :: Multimedia :: Video
Classifier: Topic :: Text Processing
Classifier: Topic :: Utilities
Requires-Dist: batchpath
Requires-Dist: chardet
